{
    "_type": "Pokemon",
    "abilities": "['Torrent', 'Defiant']",
    "against_bug": 0.5,
    "against_dark": 1.0,
    "against_dragon": 0.5,
    "against_electric": 2.0,
    "against_fairy": 0.5,
    "against_fight": 2.0,
    "against_fire": 1.0,
    "against_flying": 0.5,
    "against_ghost": 1.0,
    "against_grass": 1.0,
    "against_ground": 2.0,
    "against_ice": 0.25,
    "against_normal": 0.5,
    "against_poison": 0.0,
    "against_psychic": 0.5,
    "against_rock": 0.5,
    "against_steel": 0.25,
    "against_water": 0.5,
    "attack": 86.0,
    "base_egg_steps": 5120.0,
    "base_happiness": 70.0,
    "base_total": 530.0,
    "capture_rate": 45.0,
    "classfication": "Emperor Pok\u00e9mon",
    "defense": 88.0,
    "experience_growth": 1059860.0,
    "height_m": 1.7,
    "hp": 84.0,
    "japanese_name": "Emperte\u30a8\u30f3\u30da\u30eb\u30c8",
    "name": "Empoleon",
    "percentage_male": 88.1,
    "pokedex_number": 395.0,
    "sp_attack": 111.0,
    "sp_defense": 101.0,
    "speed": 60.0,
    "type1": "water",
    "type2": "steel",
    "weight_kg": 84.5,
    "generation": 4.0,
    "is_legendary": 0.0
}