{
    "_type": "Pokemon",
    "abilities": "['Iron Barbs', 'Anticipation']",
    "against_bug": 1.0,
    "against_dark": 1.0,
    "against_dragon": 0.5,
    "against_electric": 0.5,
    "against_fairy": 0.5,
    "against_fight": 2.0,
    "against_fire": 4.0,
    "against_flying": 1.0,
    "against_ghost": 1.0,
    "against_grass": 0.25,
    "against_ground": 1.0,
    "against_ice": 1.0,
    "against_normal": 0.5,
    "against_poison": 0.0,
    "against_psychic": 0.5,
    "against_rock": 0.5,
    "against_steel": 0.5,
    "against_water": 0.5,
    "attack": 94.0,
    "base_egg_steps": 5120.0,
    "base_happiness": 70.0,
    "base_total": 489.0,
    "capture_rate": 90.0,
    "classfication": "Thorn Pod Pok\u00e9mon",
    "defense": 131.0,
    "experience_growth": 1000000.0,
    "height_m": 1.0,
    "hp": 74.0,
    "japanese_name": "Nutrey\u30ca\u30c3\u30c8\u30ec\u30a4",
    "name": "Ferrothorn",
    "percentage_male": 50.0,
    "pokedex_number": 598.0,
    "sp_attack": 54.0,
    "sp_defense": 116.0,
    "speed": 20.0,
    "type1": "grass",
    "type2": "steel",
    "weight_kg": 110.0,
    "generation": 5.0,
    "is_legendary": 0.0
}